cellmap_schemas/__about__.py
cellmap_schemas/__init__.py
cellmap_schemas/annotation.py
cellmap_schemas/base.py
cellmap_schemas/cli.py
cellmap_schemas/n5_wrap.py
cellmap_schemas/py.typed
cellmap_schemas/multiscale/__init__.py
cellmap_schemas/multiscale/cosem.py
cellmap_schemas/multiscale/neuroglancer_n5.py
cellmap_schemas-0.8.1.dist-info/METADATA
cellmap_schemas-0.8.1.dist-info/WHEEL
cellmap_schemas-0.8.1.dist-info/licenses/LICENSE
cellmap_schemas-0.8.1.dist-info/RECORD
